<metadata xml:lang="en"><Esri><CreaDate>20150323</CreaDate><CreaTime>16462500</CreaTime><ArcGISFormat>1.0</ArcGISFormat><SyncOnce>FALSE</SyncOnce><DataProperties><itemProps><itemName Sync="TRUE">Newport Elevation Points</itemName><itemSize Sync="TRUE">0.043</itemSize><itemLocation><linkage Sync="TRUE">file://\\IGSWBWWBLT00569\C$\Users\cfreeman\Desktop\SWCSC Data Transfer\1 SWCSC Elevation Shapefiles\6 Newport\Newport Elevation Points.shp</linkage><protocol Sync="TRUE">Local Area Network</protocol></itemLocation><nativeExtBox><westBL Sync="TRUE">417585.153220</westBL><eastBL Sync="TRUE">419427.735500</eastBL><southBL Sync="TRUE">3723163.096970</southBL><northBL Sync="TRUE">3723960.412930</northBL><exTypeCode Sync="TRUE">1</exTypeCode></nativeExtBox><imsContentType Sync="TRUE">002</imsContentType></itemProps><copyHistory><copy source="V:\GIS Files\Climate_Change_GIS\SWCSC\Studysites\Newport\Maps\Newport_ver2\NewportKrigingPnts_FINAL" dest="\\IGSWBWWBFS00237\Vallejo\GIS Files\Climate_Change_GIS\SWCSC\Studysites\Newport\Maps\Newport site map Final\NewportKrigingPnts_FINAL" date="20140630" time="15240600"/></copyHistory><coordRef><type Sync="TRUE">Projected</type><geogcsn Sync="TRUE">GCS_North_American_1983</geogcsn><csUnits Sync="TRUE">Linear Unit: Meter (1.000000)</csUnits><projcsn Sync="TRUE">NAD_1983_UTM_Zone_11N</projcsn><peXml Sync="TRUE">&lt;ProjectedCoordinateSystem xsi:type='typens:ProjectedCoordinateSystem' xmlns:xsi='http://www.w3.org/2001/XMLSchema-instance' xmlns:xs='http://www.w3.org/2001/XMLSchema' xmlns:typens='http://www.esri.com/schemas/ArcGIS/10.1'&gt;&lt;WKT&gt;PROJCS[&amp;quot;NAD_1983_UTM_Zone_11N&amp;quot;,GEOGCS[&amp;quot;GCS_North_American_1983&amp;quot;,DATUM[&amp;quot;D_North_American_1983&amp;quot;,SPHEROID[&amp;quot;GRS_1980&amp;quot;,6378137.0,298.257222101]],PRIMEM[&amp;quot;Greenwich&amp;quot;,0.0],UNIT[&amp;quot;Degree&amp;quot;,0.0174532925199433]],PROJECTION[&amp;quot;Transverse_Mercator&amp;quot;],PARAMETER[&amp;quot;False_Easting&amp;quot;,500000.0],PARAMETER[&amp;quot;False_Northing&amp;quot;,0.0],PARAMETER[&amp;quot;Central_Meridian&amp;quot;,-117.0],PARAMETER[&amp;quot;Scale_Factor&amp;quot;,0.9996],PARAMETER[&amp;quot;Latitude_Of_Origin&amp;quot;,0.0],UNIT[&amp;quot;Meter&amp;quot;,1.0],AUTHORITY[&amp;quot;EPSG&amp;quot;,26911]]&lt;/WKT&gt;&lt;XOrigin&gt;-5120900&lt;/XOrigin&gt;&lt;YOrigin&gt;-9998100&lt;/YOrigin&gt;&lt;XYScale&gt;450445547.3910538&lt;/XYScale&gt;&lt;ZOrigin&gt;-1072.2175735000001&lt;/ZOrigin&gt;&lt;ZScale&gt;4194304001953.124&lt;/ZScale&gt;&lt;MOrigin&gt;-100000&lt;/MOrigin&gt;&lt;MScale&gt;10000&lt;/MScale&gt;&lt;XYTolerance&gt;0.001&lt;/XYTolerance&gt;&lt;ZTolerance&gt;0.001&lt;/ZTolerance&gt;&lt;MTolerance&gt;0.001&lt;/MTolerance&gt;&lt;HighPrecision&gt;true&lt;/HighPrecision&gt;&lt;WKID&gt;26911&lt;/WKID&gt;&lt;LatestWKID&gt;26911&lt;/LatestWKID&gt;&lt;/ProjectedCoordinateSystem&gt;</peXml></coordRef></DataProperties><SyncDate>20160303</SyncDate><SyncTime>10301100</SyncTime><ModDate>20160303</ModDate><ModTime>10303300</ModTime><ArcGISstyle>FGDC CSDGM Metadata</ArcGISstyle><scaleRange><minScale>150000000</minScale><maxScale>5000</maxScale></scaleRange><ArcGISProfile>FGDC</ArcGISProfile></Esri><mdContact><rpIndName>Karen Thorne</rpIndName><rpOrgName>USGS Western Ecological Research Center </rpOrgName><rpPosName>Research Ecologist</rpPosName><role><RoleCd value="006"/></role><rpCntInfo><cntAddress addressType="both"><delPoint>505 Azuar Dr.</delPoint><city>Vallejo</city><adminArea>CA</adminArea><postCode>94592</postCode><eMailAdd>kthorne@usgs.gov</eMailAdd><country>US</country></cntAddress><cntPhone><voiceNum>707 562 3000</voiceNum></cntPhone></rpCntInfo><displayName>Karen Thorne</displayName></mdContact><distInfo><distFormat><formatVer>1</formatVer><formatName Sync="TRUE">Shapefile</formatName></distFormat><distTranOps><transSize Sync="TRUE">0.043</transSize></distTranOps></distInfo><dataIdInfo><idCitation><date><pubDate>2015-05-01T00:00:00</pubDate></date><citRespParty><rpIndName>Karen Thorne</rpIndName><rpOrgName>USGS Western Ecological Research Center </rpOrgName><rpPosName>Research Ecologist</rpPosName><role><RoleCd value="006"/></role><rpCntInfo><cntAddress addressType="both"><delPoint>505 Azuar Dr.</delPoint><city>Vallejo</city><adminArea>CA</adminArea><postCode>94592</postCode><eMailAdd>kthorne@usgs.gov</eMailAdd><country>US</country></cntAddress><cntPhone><voiceNum>707 562 3000</voiceNum></cntPhone></rpCntInfo></citRespParty><resTitle Sync="TRUE">Newport Elevation Points</resTitle><presForm><PresFormCd value="005" Sync="TRUE"/></presForm></idCitation><dataExt xmlns=""><exDesc>Elevation surveys were conducted between the summer and fall of 2012.</exDesc><tempEle><TempExtent><exTemp><TM_Period xmlns=""><tmBegin>2012-05-01T00:00:00</tmBegin><tmEnd>2012-11-30T00:00:00</tmEnd></TM_Period></exTemp></TempExtent></tempEle><vertEle xmlns=""><vertMinVal Sync="TRUE">0.770830</vertMinVal><vertMaxVal Sync="TRUE">2.277670</vertMaxVal></vertEle></dataExt><idPurp>At the state level, California has highlighted coastal ecosystems as important areas susceptible to climate change and have prioritized research to assist in adaptation planning for resource management and ecosystem services. The information emerging from our CERCC network will provide local managers and decision makers with the information they need to address endangered and threatened species management, wetland conservation, anadromous fish and migratory bird management and habitat conservation and recovery plans while making informed decisions on habitat resiliency and land acquisition planning that effectively considers the effects of climate change. Our CERCC network is a research model that can be potentially transferred to other coastal regions throughout the US.
The overarching goal of our research was to use site-specific data to develop local and regionally-applicable climate change models that inform management of tidal wetlands along the Pacific Northwest coast. Our overarching questions were: (1) how do tidal marsh site characteristics vary across estuaries, and (2) does tidal marsh susceptibility to SLR vary along a latitudinal gradient and between estuaries? We addressed these questions with three specific objectives: (1) measure topographical and ecological characteristics (e.g., elevation, tidal range, vegetation composition) for tidal marsh and intertidal mudflats, (2) model SLR vulnerability of these habitats, and (3) examine spatial variability of these projected changes along the latitudinal gradient of the California coast.
 
</idPurp><idAbs>&lt;DIV STYLE="text-align:Left;"&gt;&lt;DIV&gt;&lt;DIV&gt;&lt;P&gt;&lt;SPAN&gt;&lt;SPAN&gt;To assess the current topography of the tidal marshes we conducted survey-grade elevation surveys at all sites between 2009 and 2013 using a Leica RX1200 Real Time Kinematic (RTK)&lt;/SPAN&gt;&lt;/SPAN&gt;&lt;SPAN /&gt;&lt;SPAN /&gt;&lt;SPAN&gt;&lt;SPAN&gt;Global Positioning System (GPS) rover (±1 cm horizontal, ±2 cm vertical accuracy; Leica Geosystems Inc., Norcross, GA; &lt;/SPAN&gt;&lt;/SPAN&gt;&lt;SPAN&gt;&lt;SPAN&gt;Figure &lt;/SPAN&gt;&lt;/SPAN&gt;&lt;SPAN&gt;&lt;SPAN&gt;4&lt;/SPAN&gt;&lt;/SPAN&gt;&lt;SPAN&gt;&lt;SPAN&gt;). At sites with RTK network coverage (San Pablo, Petaluma, Pt. Mugu, and Newport), rover positions were received in real time from the Leica Smartnet system via a CDMA modem (&lt;/SPAN&gt;&lt;/SPAN&gt;&lt;A href="http://www.lecia-geosystems.com"&gt;&lt;SPAN&gt;&lt;SPAN&gt;www.lecia-geosystems.com&lt;/SPAN&gt;&lt;/SPAN&gt;&lt;/A&gt;&lt;SPAN&gt;&lt;SPAN&gt;). At sites without network coverage (Humboldt, Bolinas, Morro and Tijuana), rover positions were received in real time from a Leica GS10 antenna base station via radio link. When using the base station, we adjusted all elevation measurements using an OPUS correction (www.ngs.noaa.gov/OPUS). We used the WGS84 ellipsoid model for vertical and horizontal positioning. We verified rover accuracy and precision by measuring positions at local National Geodetic Survey (NGS) benchmarks and temporary benchmarks established at each site (&lt;/SPAN&gt;&lt;/SPAN&gt;&lt;SPAN&gt;&lt;SPAN&gt;Table &lt;/SPAN&gt;&lt;/SPAN&gt;&lt;SPAN&gt;&lt;SPAN&gt;1&lt;/SPAN&gt;&lt;/SPAN&gt;&lt;SPAN&gt;&lt;SPAN&gt;). Average measured vertical errors at benchmarks were 1-2 cm throughout the study, comparable to the stated error of the GPS. &lt;/SPAN&gt;&lt;/SPAN&gt;&lt;/P&gt;&lt;P&gt;&lt;SPAN&gt;&lt;SPAN&gt;At each site, we surveyed marsh surface elevation along transects oriented perpendicular to the major tidal sediment source, with a survey point taken every 12.5 m; 50 m separated transect lines. We used the Geoid09 model to calculate orthometric heights from ellipsoid values (m, NAVD88; North American Vertical Datum of 1988) and projected all points to NAD83 UTM zone 10 or zone 11 using Leica GeoOffice (Leica Geosystems Inc, Norcross, GA, v. 7.0.1).&lt;/SPAN&gt;&lt;/SPAN&gt;&lt;/P&gt;&lt;P&gt;&lt;SPAN&gt;&lt;SPAN&gt;We synthesized the elevation survey data to create a digital elevation model (DEM) at each site in ArcGIS 10.2.1 Spatial Analyst (ESRI 2013; Redlands, CA) with exponential ordinary kriging methods (5 x 5 m&lt;/SPAN&gt;&lt;/SPAN&gt;&lt;SPAN /&gt;&lt;SPAN /&gt;&lt;SPAN&gt;&lt;SPAN&gt;cell size) after adjusting model parameters to minimize the root-mean-square error (RMS). We used elevation models as the baseline conditions for subsequent analyses in this study including tidal inundation patterns, SLR response modeling, and mapping of sites by specific elevation (flooding) zones. &lt;/SPAN&gt;&lt;/SPAN&gt;&lt;/P&gt;&lt;P STYLE="margin:0 0 0 0;"&gt;&lt;SPAN /&gt;&lt;/P&gt;&lt;P&gt;&lt;SPAN /&gt;&lt;/P&gt;&lt;/DIV&gt;&lt;/DIV&gt;&lt;/DIV&gt;</idAbs><searchKeys><keyword>Newport Bay</keyword><keyword>salt marsh</keyword><keyword>elevation surveys</keyword></searchKeys><dataChar><CharSetCd value="004"/></dataChar><idStatus><ProgCd value="001"/></idStatus><resMaint><maintFreq><MaintFreqCd value="011"/></maintFreq></resMaint><envirDesc Sync="TRUE">Microsoft Windows 7 Version 6.1 (Build 7601) Service Pack 1; Esri ArcGIS 10.2.0.3389</envirDesc><dataLang><languageCode value="eng" Sync="TRUE"/><countryCode value="USA" Sync="TRUE"/></dataLang><spatRpType><SpatRepTypCd value="001" Sync="TRUE"/></spatRpType><dataExt xmlns=""><geoEle xmlns=""><GeoBndBox esriExtentType="search"><exTypeCode Sync="TRUE">1</exTypeCode><westBL Sync="TRUE">-117.888821</westBL><eastBL Sync="TRUE">-117.868879</eastBL><northBL Sync="TRUE">33.652454</northBL><southBL Sync="TRUE">33.645122</southBL></GeoBndBox></geoEle></dataExt></dataIdInfo><contInfo><ImgDesc><attDesc>elevation</attDesc><trianInd>False</trianInd><radCalDatAv>False</radCalDatAv><camCalInAv>False</camCalInAv><filmDistInAv>False</filmDistInAv><lensDistInAv>False</lensDistInAv><covDim><Band><valUnit><UOM type="length"><unitSymbol>m</unitSymbol></UOM></valUnit></Band></covDim></ImgDesc></contInfo><eainfo><detailed Name="Newport Elevation Points" xmlns=""><enttyp><enttypl Sync="FALSE">Newport Elevation Points</enttypl><enttypt Sync="TRUE">Feature Class</enttypt><enttypc Sync="TRUE">1012</enttypc><enttypd>Elevation Points</enttypd><enttypds>USGS</enttypds></enttyp><attr xmlns=""><attrlabl Sync="TRUE">FID</attrlabl><attalias Sync="TRUE">FID</attalias><attrtype Sync="TRUE">OID</attrtype><attwidth Sync="TRUE">4</attwidth><atprecis Sync="TRUE">0</atprecis><attscale Sync="TRUE">0</attscale><attrdef Sync="TRUE">Internal feature number.</attrdef><attrdefs Sync="TRUE">Esri</attrdefs><attrdomv><udom Sync="TRUE">Sequential unique whole numbers that are automatically generated.</udom></attrdomv></attr><attr xmlns=""><attrlabl Sync="TRUE">Shape</attrlabl><attalias Sync="TRUE">Shape</attalias><attrtype Sync="TRUE">Geometry</attrtype><attwidth Sync="TRUE">0</attwidth><atprecis Sync="TRUE">0</atprecis><attscale Sync="TRUE">0</attscale><attrdef Sync="TRUE">Feature geometry.</attrdef><attrdefs Sync="TRUE">Esri</attrdefs><attrdomv><udom Sync="TRUE">Coordinates defining the features.</udom></attrdomv></attr><attr xmlns=""><attrlabl Sync="TRUE">Date_Time</attrlabl><attalias Sync="TRUE">Date_Time</attalias><attrtype Sync="TRUE">String</attrtype><attwidth Sync="TRUE">254</attwidth><atprecis Sync="TRUE">0</atprecis><attscale Sync="TRUE">0</attscale><attrdef>Date and time of when the elevation point was measured</attrdef><attrdefs>USGS</attrdefs></attr><attr xmlns=""><attrlabl Sync="TRUE">Easting_Lo</attrlabl><attalias Sync="TRUE">Easting_Lo</attalias><attrtype Sync="TRUE">Double</attrtype><attwidth Sync="TRUE">16</attwidth><atprecis Sync="TRUE">15</atprecis><attscale Sync="TRUE">6</attscale><attrdef>Easting coordinate of the measured point in NAVD88 UTM zone11</attrdef><attrdefs>USGS</attrdefs></attr><attr xmlns=""><attrlabl Sync="TRUE">Northing_L</attrlabl><attalias Sync="TRUE">Northing_L</attalias><attrtype Sync="TRUE">Double</attrtype><attwidth Sync="TRUE">16</attwidth><atprecis Sync="TRUE">15</atprecis><attscale Sync="TRUE">6</attscale><attrdef>Northing coordinate of the measured point in NAVD88 UTM zone 11</attrdef><attrdefs>USGS</attrdefs></attr><attr xmlns=""><attrlabl Sync="TRUE">Ortho_Heig</attrlabl><attalias Sync="TRUE">Ortho_Heig</attalias><attrtype Sync="TRUE">Double</attrtype><attwidth Sync="TRUE">16</attwidth><atprecis Sync="TRUE">15</atprecis><attscale Sync="TRUE">6</attscale><attrdef>Orthometric height of the elevation point measured in NAVD88 UTM zone11</attrdef><attrdefs>USGS</attrdefs></attr><attr xmlns=""><attrlabl Sync="TRUE">Point_ID</attrlabl><attalias Sync="TRUE">Point_ID</attalias><attrtype Sync="TRUE">String</attrtype><attwidth Sync="TRUE">254</attwidth><atprecis Sync="TRUE">0</atprecis><attscale Sync="TRUE">0</attscale><attrdef>Unique id to identify elevation points</attrdef><attrdefs>USGS</attrdefs></attr></detailed></eainfo><mdLang><languageCode value="eng" Sync="TRUE"/><countryCode value="USA" Sync="TRUE"/></mdLang><mdHrLv><ScopeCd value="005" Sync="TRUE"/></mdHrLv><mdHrLvName Sync="TRUE">dataset</mdHrLvName><spdoinfo><ptvctinf><esriterm Name="Newport Elevation Points"><efeatyp Sync="TRUE">Simple</efeatyp><efeageom code="1" Sync="TRUE"/><esritopo Sync="TRUE">FALSE</esritopo><efeacnt Sync="TRUE">1012</efeacnt><spindex Sync="TRUE">TRUE</spindex><linrefer Sync="TRUE">TRUE</linrefer></esriterm></ptvctinf></spdoinfo><mdDateSt Sync="TRUE">20160303</mdDateSt><refSysInfo><RefSystem><refSysID><identCode code="26911" Sync="TRUE"/><idCodeSpace Sync="TRUE">EPSG</idCodeSpace><idVersion Sync="TRUE">8.1.1</idVersion></refSysID></RefSystem></refSysInfo><spatRepInfo><VectSpatRep><geometObjs Name="Newport Elevation Points"><geoObjTyp><GeoObjTypCd value="004" Sync="TRUE"/></geoObjTyp><geoObjCnt Sync="TRUE">1012</geoObjCnt></geometObjs><topLvl><TopoLevCd value="001" Sync="TRUE"/></topLvl></VectSpatRep></spatRepInfo></metadata>
